jirarelease/__init__.py
jirarelease-1.2.2.dist-info/LICENSE
jirarelease-1.2.2.dist-info/WHEEL
jirarelease-1.2.2.dist-info/METADATA
jirarelease-1.2.2.dist-info/RECORD
