Metadata-Version: 2.1
Name: jirarelease
Version: 1.2.2
Summary: This is a example for jira release
Author-email: Max Leow <maxengiu@outlook.com>
Classifier: License :: OSI Approved :: MIT License
Requires-Dist: jira >=3.4.1,<3.5.0
Project-URL: Home, https://github.com/maxleow/timebased-release
